earthkit/geo/__init__.py
earthkit/geo/_version.py
earthkit/geo/constants.py
earthkit/geo/coord.py
earthkit/geo/distance.py
earthkit/geo/figure.py
earthkit/geo/rotate.py
earthkit/geo/version.py
earthkit_geo-0.2.0.dist-info/LICENSE
earthkit_geo-0.2.0.dist-info/METADATA
earthkit_geo-0.2.0.dist-info/WHEEL
earthkit_geo-0.2.0.dist-info/top_level.txt
earthkit_geo-0.2.0.dist-info/RECORD
