Metadata-Version: 2.1
Name: earthkit-geo
Version: 0.2.0
Summary: Geospatial computations
Author-email: "European Centre for Medium-Range Weather Forecasts (ECMWF)" <software.support@ecmwf.int>
License: Apache License Version 2.0
Project-URL: Documentation, https://earthkit-geo.readthedocs.io/
Project-URL: Homepage, https://github.com/ecmwf/earthkit-geo/
Project-URL: Issues, https://github.com/ecmwf/earthkit-geo/issues
Project-URL: Repository, https://github.com/ecmwf/earthkit-geo/
Classifier: Development Status :: 2 - Pre-Alpha
Classifier: Intended Audience :: Developers
Classifier: License :: OSI Approved :: Apache Software License
Classifier: Programming Language :: Python :: 3
Classifier: Programming Language :: Python :: 3.8
Classifier: Programming Language :: Python :: 3.9
Classifier: Programming Language :: Python :: 3.10
Classifier: Programming Language :: Python :: 3.11
Classifier: Programming Language :: Python :: Implementation :: CPython
Classifier: Programming Language :: Python :: Implementation :: PyPy
Classifier: Operating System :: OS Independent
Requires-Python: >=3.8
License-File: LICENSE
Requires-Dist: pyproj
Requires-Dist: scipy
Provides-Extra: test
Requires-Dist: pytest; extra == "test"
Requires-Dist: pytest-cov; extra == "test"
